[
    {
        "key": "dbln",
        "value": "%7B%22100068903804185%22%3A%22delian1i%22%2C%2261556426205089%22%3A%22L80IqZRQ%22%2C%2261562963472651%22%3A%224U1Hocm5%22%2C%22100095349618966%22%3A%22OR9ubYTh%22%2C%22100095016803089%22%3A%22NGnGEZVT%22%7D",
        "domain": "facebook.com",
        "path": "/login/device-based/",
        "hostOnly": false,
        "creation": "2024-11-19T07:19:28.677Z",
        "lastAccessed": "2024-11-19T07:19:28.678Z"
    },
    {
        "key": "sb",
        "value": "FT5KZvGZKq0GKhRrv9P2CyZX",
        "domain": "facebook.com",
        "path": "/",
        "hostOnly": false,
        "creation": "2024-11-19T07:19:28.678Z",
        "lastAccessed": "2024-11-19T07:19:28.678Z"
    },
    {
        "key": "datr",
        "value": "dD3VZmHNtfeS_VWFfubuVq4R",
        "domain": "facebook.com",
        "path": "/",
        "hostOnly": false,
        "creation": "2024-11-19T07:19:28.678Z",
        "lastAccessed": "2024-11-19T07:19:28.678Z"
    },
    {
        "key": "ps_l",
        "value": "1",
        "domain": "facebook.com",
        "path": "/",
        "hostOnly": false,
        "creation": "2024-11-19T07:19:28.678Z",
        "lastAccessed": "2024-11-19T07:19:28.678Z"
    },
    {
        "key": "ps_n",
        "value": "1",
        "domain": "facebook.com",
        "path": "/",
        "hostOnly": false,
        "creation": "2024-11-19T07:19:28.678Z",
        "lastAccessed": "2024-11-19T07:19:28.678Z"
    },
    {
        "key": "vpd",
        "value": "v1%3B708x360x2.341179847717285",
        "domain": "facebook.com",
        "path": "/",
        "hostOnly": false,
        "creation": "2024-11-19T07:19:28.678Z",
        "lastAccessed": "2024-11-19T07:19:28.678Z"
    },
    {
        "key": "dpr",
        "value": "2.574002742767334",
        "domain": "facebook.com",
        "path": "/",
        "hostOnly": false,
        "creation": "2024-11-19T07:19:28.678Z",
        "lastAccessed": "2024-11-19T07:19:28.678Z"
    },
    {
        "key": "wd",
        "value": "1142x2246",
        "domain": "facebook.com",
        "path": "/",
        "hostOnly": false,
        "creation": "2024-11-19T07:19:28.678Z",
        "lastAccessed": "2024-11-19T07:19:28.678Z"
    },
    {
        "key": "c_user",
        "value": "61550753645983",
        "domain": "facebook.com",
        "path": "/",
        "hostOnly": false,
        "creation": "2024-11-19T07:19:28.678Z",
        "lastAccessed": "2024-11-19T07:19:28.678Z"
    },
    {
        "key": "locale",
        "value": "en_GB",
        "domain": "facebook.com",
        "path": "/",
        "hostOnly": false,
        "creation": "2024-11-19T07:19:28.678Z",
        "lastAccessed": "2024-11-19T07:19:28.678Z"
    },
    {
        "key": "fbl_st",
        "value": "100734405%3BT%3A28866679",
        "domain": "facebook.com",
        "path": "/",
        "hostOnly": false,
        "creation": "2024-11-19T07:19:28.678Z",
        "lastAccessed": "2024-11-19T07:19:28.678Z"
    },
    {
        "key": "wl_cbv",
        "value": "v2%3Bclient_version%3A2677%3Btimestamp%3A1732000761",
        "domain": "facebook.com",
        "path": "/",
        "hostOnly": false,
        "creation": "2024-11-19T07:19:28.678Z",
        "lastAccessed": "2024-11-19T07:19:28.678Z"
    },
    {
        "key": "fr",
        "value": "1lk9J2f1FvszfJlYQ.AWXGmMsLcGVp3Z65_Gf1CMcScLM.BnPDv8..AAA.0.0.BnPDv8.AWWHuY9x6yk",
        "domain": "facebook.com",
        "path": "/",
        "hostOnly": false,
        "creation": "2024-11-19T07:19:28.678Z",
        "lastAccessed": "2024-11-19T07:19:28.678Z"
    },
    {
        "key": "xs",
        "value": "30%3ApZWuSs45rZKFEQ%3A2%3A1732000750%3A-1%3A14098%3A%3AAcURD58F3bLHODUfDGM-peceS2fw1LLKpYvaMWQoCA",
        "domain": "facebook.com",
        "path": "/",
        "hostOnly": false,
        "creation": "2024-11-19T07:19:28.678Z",
        "lastAccessed": "2024-11-19T07:19:28.678Z"
    }
]
