[
    {
        "key": "dbln",
        "value": "%7B%2261550753645983%22%3A%22AvD7XmhG%22%7D",
        "domain": "facebook.com",
        "path": "/login/device-based/",
        "hostOnly": false,
        "creation": "2024-11-18T14:06:06.549Z",
        "lastAccessed": "2024-11-18T14:06:06.549Z"
    },
    {
        "key": "datr",
        "value": "doIwZwvbGwWkK5Yty6mx51bo",
        "domain": "facebook.com",
        "path": "/",
        "hostOnly": false,
        "creation": "2024-11-18T14:06:06.549Z",
        "lastAccessed": "2024-11-18T14:06:06.549Z"
    },
    {
        "key": "sb",
        "value": "doIwZwJ0tneIdIxv5Q4VkhJ1",
        "domain": "facebook.com",
        "path": "/",
        "hostOnly": false,
        "creation": "2024-11-18T14:06:06.549Z",
        "lastAccessed": "2024-11-18T14:06:06.549Z"
    },
    {
        "key": "vpd",
        "value": "v1%3B665x360x1.500488042831421",
        "domain": "facebook.com",
        "path": "/",
        "hostOnly": false,
        "creation": "2024-11-18T14:06:06.549Z",
        "lastAccessed": "2024-11-18T14:06:06.549Z"
    },
    {
        "key": "ps_l",
        "value": "1",
        "domain": "facebook.com",
        "path": "/",
        "hostOnly": false,
        "creation": "2024-11-18T14:06:06.549Z",
        "lastAccessed": "2024-11-18T14:06:06.549Z"
    },
    {
        "key": "ps_n",
        "value": "1",
        "domain": "facebook.com",
        "path": "/",
        "hostOnly": false,
        "creation": "2024-11-18T14:06:06.549Z",
        "lastAccessed": "2024-11-18T14:06:06.549Z"
    },
    {
        "key": "locale",
        "value": "en_GB",
        "domain": "facebook.com",
        "path": "/",
        "hostOnly": false,
        "creation": "2024-11-18T14:06:06.549Z",
        "lastAccessed": "2024-11-18T14:06:06.549Z"
    },
    {
        "key": "m_pixel_ratio",
        "value": "1.500488042831421",
        "domain": "facebook.com",
        "path": "/",
        "hostOnly": false,
        "creation": "2024-11-18T14:06:06.549Z",
        "lastAccessed": "2024-11-18T14:06:06.549Z"
    },
    {
        "key": "wd",
        "value": "720x1329",
        "domain": "facebook.com",
        "path": "/",
        "hostOnly": false,
        "creation": "2024-11-18T14:06:06.549Z",
        "lastAccessed": "2024-11-18T14:06:06.549Z"
    },
    {
        "key": "c_user",
        "value": "61550753645983",
        "domain": "facebook.com",
        "path": "/",
        "hostOnly": false,
        "creation": "2024-11-18T14:06:06.549Z",
        "lastAccessed": "2024-11-18T14:06:06.549Z"
    },
    {
        "key": "fr",
        "value": "0rnzx0lB7MIRvmJWg.AWWVOScmkxemK4GvNoG9PuTo2lI.BnMIJ2..AAA.0.0.BnO0nB.AWW6LFKxS_g",
        "domain": "facebook.com",
        "path": "/",
        "hostOnly": false,
        "creation": "2024-11-18T14:06:06.549Z",
        "lastAccessed": "2024-11-18T14:06:06.549Z"
    },
    {
        "key": "xs",
        "value": "3%3ANyu2PlwN4Bb2pg%3A2%3A1731938753%3A-1%3A14098",
        "domain": "facebook.com",
        "path": "/",
        "hostOnly": false,
        "creation": "2024-11-18T14:06:06.549Z",
        "lastAccessed": "2024-11-18T14:06:06.549Z"
    },
    {
        "key": "fbl_st",
        "value": "101238193%3BT%3A28865645",
        "domain": "facebook.com",
        "path": "/",
        "hostOnly": false,
        "creation": "2024-11-18T14:06:06.549Z",
        "lastAccessed": "2024-11-18T14:06:06.549Z"
    },
    {
        "key": "wl_cbv",
        "value": "v2%3Bclient_version%3A2675%3Btimestamp%3A1731938759",
        "domain": "facebook.com",
        "path": "/",
        "hostOnly": false,
        "creation": "2024-11-18T14:06:06.549Z",
        "lastAccessed": "2024-11-18T14:06:06.549Z"
    }
]
